viewwork/__init__.py
viewwork/admin.py
viewwork/apps.py
viewwork/forms.py
viewwork/metaclass.py
viewwork/models.py
viewwork/settings.py
viewwork/urls.py
viewwork/utils.py
viewwork/views.py
viewwork/locale/en/LC_MESSAGES/django.mo
viewwork/locale/en/LC_MESSAGES/django.po
viewwork/locale/ru/LC_MESSAGES/django.mo
viewwork/locale/ru/LC_MESSAGES/django.po
viewwork/management/__init__.py
viewwork/management/commands/__init__.py
viewwork/management/commands/vw_namespace.py
viewwork/migrations/0001_initial.py
viewwork/migrations/0002_auto_20210709_1622.py
viewwork/migrations/0003_menu_i18n.py
viewwork/migrations/0004_enabled_hidden.py
viewwork/migrations/0005_fix_view_name.py
viewwork/migrations/__init__.py
django_viewwork-0.8.0.dist-info/LICENSE
django_viewwork-0.8.0.dist-info/METADATA
django_viewwork-0.8.0.dist-info/WHEEL
django_viewwork-0.8.0.dist-info/top_level.txt
django_viewwork-0.8.0.dist-info/RECORD
